brainhurt/__init__.py
brainhurt/__main__.py
brainhurt/brainhurt.py
brainhurt/error.py
brainhurt/iota.py
brainhurt-0.1.0.dist-info/Authors.rst
brainhurt-0.1.0.dist-info/LICENSE
brainhurt-0.1.0.dist-info/METADATA
brainhurt-0.1.0.dist-info/WHEEL
brainhurt-0.1.0.dist-info/top_level.txt
brainhurt-0.1.0.dist-info/RECORD
