Metadata-Version: 2.1
Name: brainhurt
Version: 0.1.0
Summary: This is an Interpreter and debugger for the programming language `BrainFuck` written in `Python`
Home-page: https://github.com/PankajVishw50/brainhurt
Author: Pankaj Vishwakarma
Author-email: vishw.dev.1000@gmail.com
Keywords: pankaj,pankaj vishw,brainfuck,brainhurt,brainfuck compiler,brainfuck interpreter,brainfuck debugger,debugger,interpretter,compiler
Classifier: Development Status :: 5 - Production/Stable
Classifier: Natural Language :: English
Classifier: Programming Language :: Python
Classifier: Programming Language :: Python :: 3
Classifier: Operating System :: OS Independent
Classifier: License :: OSI Approved :: MIT License
Classifier: Topic :: Software Development :: Debuggers
Classifier: Topic :: Software Development :: Interpreters
Classifier: Topic :: Software Development :: Compilers
Requires-Python: >=3.7
License-File: LICENSE
License-File: Authors.rst
